odoo/addons/l10n_th_base_sequence/README.rst
odoo/addons/l10n_th_base_sequence/__init__.py
odoo/addons/l10n_th_base_sequence/__manifest__.py
odoo/addons/l10n_th_base_sequence/i18n/l10n_th_base_sequence.pot
odoo/addons/l10n_th_base_sequence/models/__init__.py
odoo/addons/l10n_th_base_sequence/models/ir_sequence.py
odoo/addons/l10n_th_base_sequence/models/ir_sequence_date_range.py
odoo/addons/l10n_th_base_sequence/readme/CONTRIBUTORS.md
odoo/addons/l10n_th_base_sequence/readme/DESCRIPTION.md
odoo/addons/l10n_th_base_sequence/static/description/icon.png
odoo/addons/l10n_th_base_sequence/static/description/index.html
odoo/addons/l10n_th_base_sequence/tests/__init__.py
odoo/addons/l10n_th_base_sequence/tests/test_ir_sequence.py
odoo/addons/l10n_th_base_sequence/tests/test_ir_sequence_date_range.py
odoo/addons/l10n_th_base_sequence/views/ir_sequence_view.xml
odoo_addon_l10n_th_base_sequence-18.0.1.0.0.3.dist-info/METADATA
odoo_addon_l10n_th_base_sequence-18.0.1.0.0.3.dist-info/WHEEL
odoo_addon_l10n_th_base_sequence-18.0.1.0.0.3.dist-info/top_level.txt
odoo_addon_l10n_th_base_sequence-18.0.1.0.0.3.dist-info/RECORD
